{ "height":100,
 "layers":[
        {
         "draworder":"topdown",
         "name":"Camada de Objetos 1",
         "objects":[
                {
                 "gid":1,
                 "height":276,
                 "id":1,
                 "name":"",
                 "rotation":0,
                 "type":"",
                 "visible":true,
                 "width":276,
                 "x":2,
                 "y":3204
                }, 
                {
                 "gid":1,
                 "height":354,
                 "id":2,
                 "name":"",
                 "rotation":0,
                 "type":"",
                 "visible":true,
                 "width":762,
                 "x":640,
                 "y":2912
                }, 
                {
                 "gid":1,
                 "height":656,
                 "id":3,
                 "name":"",
                 "rotation":0,
                 "type":"",
                 "visible":true,
                 "width":278,
                 "x":96,
                 "y":2688
                }],
         "opacity":1,
         "type":"objectgroup",
         "visible":true,
         "x":0,
         "y":0
        }],
 "nextobjectid":4,
 "orientation":"orthogonal",
 "renderorder":"right-down",
 "tiledversion":"1.0.3",
 "tileheight":32,
 "tilesets":[
        {
         "columns":8,
         "firstgid":1,
         "image":"..\/Downloads\/aula13_tiled_tmx\/assets\/map-objects.png",
         "imageheight":64,
         "imagewidth":256,
         "margin":0,
         "name":"map-objects",
         "spacing":0,
         "tilecount":16,
         "tileheight":32,
         "tilewidth":32
        }],
 "tilewidth":32,
 "type":"map",
 "version":1,
 "width":100
}